{
  "current": {
    "color_body_bg": "#ffffff",
    "color_body_text": "#000000",
    "color_button": "#000000",
    "color_button_text": "#ffffff",
    "color_sale_price": "#000000",
    "color_sale_tag": "#990000",
    "color_cart_dot": "#f75d44",
    "color_cart_dot_text": "#ffffff",
    "color_alt_bg": "#f9f9f9",
    "color_alt_text": "#000000",
    "color_announcement": "#000000",
    "color_announcement_text": "#ffffff",
    "color_newsletter": "#000000",
    "color_newsletter_text": "#fff",
    "color_drawer_background": "#ffffff",
    "color_drawer_text": "#000000",
    "color_image_text": "#ffffff",
    "color_image_overlay": "#000000",
    "color_image_overlay_opacity": 10,
    "color_image_overlay_text_shadow": 20,
    "color_small_image_bg": "#ffffff",
    "color_large_image_bg": "#000000",
    "type_header_font_family": "roboto_condensed_i7",
    "type_header_capitalize": true,
    "type_header_spacing": -25,
    "type_header_base_size": 46,
    "type_header_line_height": 1,
    "type_base_font_family": "roboto_condensed_n4",
    "type_product_capitalize": false,
    "type_base_spacing": 25,
    "type_base_size": 18,
    "type_base_line_height": 1.6,
    "button_type_style": "normal",
    "button_style": "round",
    "animate_images": true,
    "logo_loader_image": "shopify:\/\/shop_images\/ajr-logo-dark.png",
    "desktop_loader_width": 260,
    "mobile_loader_width": 160,
    "product_hover_details": false,
    "product_hover_image": true,
    "product_image_scatter": false,
    "product_grid_image_size": "natural",
    "enable_swatches": true,
    "cart_type": "drawer",
    "social_instagram_link": "https:\/\/instagram.com\/ajrcollectionn",
    "social_facebook_link": "https:\/\/www.facebook.com\/Ajrcollectionn",
    "share_twitter": false,
    "share_pinterest": false,
    "checkout_logo_image": "shopify:\/\/shop_images\/ajr-logo-dark.png",
    "checkout_logo_position": "left",
    "checkout_logo_size": "medium",
    "checkout_body_background_color": "#ffffff",
    "checkout_input_background_color_mode": "white",
    "checkout_sidebar_background_color": "#fafafa",
    "checkout_heading_font": "Helvetica Neue",
    "checkout_body_font": "Helvetica Neue",
    "checkout_accent_color": "#111111",
    "checkout_button_color": "#111111",
    "checkout_error_color": "#ff6d6d",
    "animate_page_transition_style": "page-logo",
    "checkout_banner_background_color": "#ffffff",
    "checkout_call_to_action_color": "#a26b25",
    "checkout_use_header_image": false,
    "product_video_style": "muted",
    "sections": {
      "header": {
        "type": "header",
        "settings": {
          "header_style": "bar",
          "main_menu_alignment": "right",
          "sticky_index": true,
          "sticky_collection": false,
          "header_search_enable": true,
          "logo": "shopify:\/\/shop_images\/ajr-logo-dark.png",
          "logo-inverted": "shopify:\/\/shop_images\/ajr-logo-light.png",
          "desktop_logo_width": 150,
          "mobile_logo_width": 120,
          "logo_hide_mobile": true,
          "main_menu_link_list": "main-menu",
          "show_announcement": true,
          "show_announcement_home_only": false,
          "announcement_text": "Free shipping and returns",
          "announcement_link": ""
        }
      },
      "footer": {
        "type": "footer",
        "settings": {
          "show_newsletter": true,
          "newsletter_title": "Join the club",
          "newsletter_richtext": "",
          "show_locale_selector": true,
          "show_currency_selector": true,
          "show_currency_flags": true,
          "show_social_icons": true,
          "menu": "information",
          "menu_2": "ajrcollection-footer",
          "contact": "<ul class=\"no-bullets inline-list site-footer__linklist\">\n<li><a href=\"mailto:info@ajrcollection.com\" target=\"_blank\">info@ajrcollection.com<\/a><\/li>\n<li><a href=\"tel:+4552449362\">+4552449362<\/a><\/li>\n<\/ul>",
          "show_payment_icons": false,
          "show_copyright": false,
          "copyright_text": ""
        }
      },
      "newsletter-popup": {
        "type": "newsletter-popup",
        "settings": {
          "mode": "disabled",
          "popup_seconds": 5,
          "popup_days": 30,
          "popup_title": "Sign up and save",
          "popup_text": "<p>Entice customers to sign up for your mailing list with discounts or exclusive offers.<\/p>",
          "enable_newsletter": true,
          "button_label": "",
          "button_link": ""
        }
      },
      "product-recommendations": {
        "type": "product-recommendations",
        "settings": {
          "show_product_recommendations": true
        }
      },
      "social": {
        "type": "social",
        "blocks": {
          "6f030d60-6851-4cdd-99a9-93578113966a": {
            "type": "post",
            "settings": {
              "image": "shopify:\/\/shop_images\/Skaermbillede_2022-02-23_kl._09.14.13.png",
              "link": "https:\/\/www.instagram.com\/p\/CQ0FTqyjZFy\/",
              "product": "",
              "account": "ajrcollectionn",
              "caption": "Lets play some football at the desert with the brand new (Grey) AjrUnderwear🏜🌵⚽️...",
              "likes": ""
            }
          },
          "269eb1bf-de7f-49e2-912c-c2e33be3ad69": {
            "type": "post",
            "settings": {
              "image": "shopify:\/\/shop_images\/Skaermbillede_2022-02-23_kl._09.39.09.png",
              "link": "https:\/\/www.instagram.com\/p\/CKnt5yUBF50\/",
              "product": "",
              "account": "ajrcollectionn",
              "caption": "#Repost • This is @nadi9nadim 🦖 . Nadia Nadim is a Danish football player who plays as a striker in...",
              "likes": ""
            }
          },
          "c150385c-852c-4e8d-b77a-3d6cd6c422bf": {
            "type": "post",
            "settings": {
              "image": "shopify:\/\/shop_images\/Skaermbillede_2022-02-23_kl._09.45.45.png",
              "link": "https:\/\/www.instagram.com\/p\/CKe6SGaBeVG\/",
              "product": "",
              "account": "ajrcollectionn",
              "caption": "TRAILER OF SHORTA 🎬 @ajrcollectionn  ⭐️Tarek ZAYAT is a young danish actor...",
              "likes": ""
            }
          },
          "4116f75c-f6d9-479e-9864-599ba68cc76e": {
            "type": "post",
            "settings": {
              "image": "shopify:\/\/shop_images\/Skaermbillede_2022-02-23_kl._09.49.16.png",
              "link": "https:\/\/www.instagram.com\/p\/CKe0w3kBobJ\/",
              "product": "",
              "account": "ajrcollectionn",
              "caption": "@kingarturo23oficial 👑 • Arturo Erasmo Vidal Pardo is a Chilean professional...",
              "likes": ""
            }
          },
          "d11d94d6-346c-4f72-9b22-c04c13ebfffa": {
            "type": "post",
            "settings": {
              "image": "shopify:\/\/shop_images\/Skaermbillede_2022-02-23_kl._09.55.01.png",
              "link": "https:\/\/www.instagram.com\/p\/CKUtY2Vhqq_\/",
              "product": "",
              "account": "ajrcollectionn",
              "caption": "THE Danish Champion 🇩🇰🥇  An undefeated danish young talent get in touch with #AjrUnderwear 💪🏽",
              "likes": ""
            }
          },
          "147ec469-26a1-4f96-832f-8d857616ee74": {
            "type": "post",
            "settings": {
              "image": "shopify:\/\/shop_images\/Skaermbillede_2022-02-23_kl._09.56.25.png",
              "link": "https:\/\/www.instagram.com\/p\/CKPPK2nBaHO\/",
              "product": "",
              "account": "ajrcollectionn",
              "caption": "#AjrUnderwear  We have produced all of our products using natural materials of the highest quality...",
              "likes": ""
            }
          },
          "cbef6498-1a4f-4003-947d-8a95cd5dc1b3": {
            "type": "post",
            "settings": {
              "image": "shopify:\/\/shop_images\/Skaermbillede_2022-02-23_kl._10.05.54.png",
              "link": "https:\/\/www.instagram.com\/p\/B8lb9oqBrbF\/",
              "product": "",
              "account": "ajrcollectionn",
              "caption": "Papiss Cissé enjoying the #Ajrunderwear. If you want to try - Get yours now.. at @ajrcollectionn ☝️",
              "likes": ""
            }
          },
          "030e7838-bda3-4244-b53e-520265b73aa3": {
            "type": "post",
            "settings": {
              "image": "shopify:\/\/shop_images\/Skaermbillede_2022-02-23_kl._10.07.27.png",
              "link": "https:\/\/www.instagram.com\/p\/B8DnEAkhNun\/",
              "product": "",
              "account": "ajrcollectionn",
              "caption": "@nickyandersen wearing #AjrUnderwear. #AJRpromotions",
              "likes": ""
            }
          },
          "dada92da-7a36-4f8b-80d2-99d391e867fa": {
            "type": "post",
            "settings": {
              "image": "shopify:\/\/shop_images\/Skaermbillede_2022-02-23_kl._10.08.57.png",
              "link": "https:\/\/www.instagram.com\/p\/B60960zBZmg\/",
              "product": "",
              "account": "ajrcollectionn",
              "caption": "This is @gle_nn using our brand new #AjrUnderwear. What a beautiful view and amazing skills 💥⚽️🏝...",
              "likes": ""
            }
          },
          "40f1336f-9d48-4770-b1d2-c0dcf1860a76": {
            "type": "post",
            "settings": {
              "image": "shopify:\/\/shop_images\/Skaermbillede_2022-02-23_kl._10.14.39.png",
              "link": "https:\/\/www.instagram.com\/p\/B6zZvT3hqFK\/",
              "product": "",
              "account": "ajrcollectionn",
              "caption": "We are in Dubai. This is coach ROOTS he enjoyed our #AjrWear 💪🏽 This #MyAjrs is a real winner that we...",
              "likes": ""
            }
          }
        },
        "block_order": [
          "6f030d60-6851-4cdd-99a9-93578113966a",
          "269eb1bf-de7f-49e2-912c-c2e33be3ad69",
          "c150385c-852c-4e8d-b77a-3d6cd6c422bf",
          "4116f75c-f6d9-479e-9864-599ba68cc76e",
          "d11d94d6-346c-4f72-9b22-c04c13ebfffa",
          "147ec469-26a1-4f96-832f-8d857616ee74",
          "cbef6498-1a4f-4003-947d-8a95cd5dc1b3",
          "030e7838-bda3-4244-b53e-520265b73aa3",
          "dada92da-7a36-4f8b-80d2-99d391e867fa",
          "40f1336f-9d48-4770-b1d2-c0dcf1860a76"
        ],
        "settings": {
          "enable_home": true,
          "enable_product": true,
          "enable_collection": false,
          "title": "On social",
          "description": "<p>Send us yours <a href=\"https:\/\/www.instagram.com\/ajrcollectionn\/\" target=\"_blank\" title=\"https:\/\/www.instagram.com\/ajrcollectionn\/\">@ajrcollectionn<\/a><\/p>"
        }
      }
    },
    "content_for_index": []
  },
  "presets": {
    "Core": {
      "animate_images": true,
      "animate_page_transition_style": "page-logo",
      "button_style": "round",
      "button_type_style": "normal",
      "cart_type": "sticky",
      "checkout_accent_color": "#111111",
      "checkout_banner_background_color": "#ffffff",
      "checkout_body_background_color": "#ffffff",
      "checkout_body_font": "Helvetica Neue",
      "checkout_button_color": "#111111",
      "checkout_call_to_action_color": "#a26b25",
      "checkout_error_color": "#ff6d6d",
      "checkout_heading_font": "Helvetica Neue",
      "checkout_input_background_color_mode": "white",
      "checkout_logo_position": "left",
      "checkout_logo_size": "medium",
      "checkout_sidebar_background_color": "#fafafa",
      "checkout_use_header_image": false,
      "color_alt_bg": "#f9f9f9",
      "color_alt_text": "#000000",
      "color_announcement": "#000000",
      "color_announcement_text": "#ffffff",
      "color_body_bg": "#ffffff",
      "color_body_text": "#000000",
      "color_button": "#000000",
      "color_button_text": "#ffffff",
      "color_cart_dot": "#f75d44",
      "color_cart_dot_text": "#ffffff",
      "color_drawer_background": "#ffffff",
      "color_drawer_text": "#000000",
      "color_image_overlay": "#000000",
      "color_image_overlay_opacity": 10,
      "color_image_overlay_text_shadow": 20,
      "color_image_text": "#ffffff",
      "color_large_image_bg": "#000000",
      "color_newsletter": "#000000",
      "color_newsletter_text": "#fff",
      "color_sale_price": "#000000",
      "color_sale_tag": "#990000",
      "color_small_image_bg": "#ffffff",
      "desktop_loader_width": 100,
      "mobile_loader_width": 100,
      "product_grid_image_size": "natural",
      "product_hover_details": false,
      "product_hover_image": true,
      "product_image_scatter": false,
      "product_video_style": "muted",
      "type_base_font_family": "roboto_condensed_n4",
      "type_base_line_height": 1.6,
      "type_base_size": 18,
      "type_base_spacing": "25",
      "type_header_base_size": 46,
      "type_header_capitalize": true,
      "type_header_font_family": "roboto_condensed_i7",
      "type_header_line_height": 1,
      "type_header_spacing": "-25",
      "type_product_capitalize": false,
      "sections": {
        "header": {
          "type": "header",
          "settings": {
            "sticky_index": true,
            "sticky_collection": false,
            "header_search_enable": true,
            "show_announcement": false,
            "show_announcement_home_only": false
          }
        },
        "footer": {
          "type": "footer",
          "settings": {
            "show_newsletter": true,
            "show_social_icons": true,
            "menu": "footer",
            "newsletter_title": "Join the club",
            "newsletter_richtext": "",
            "show_payment_icons": false,
            "show_copyright": false
          }
        },
        "newsletter-popup": {
          "type": "newsletter-popup",
          "settings": {
            "mode": "disabled",
            "popup_seconds": 5,
            "popup_days": 30,
            "enable_newsletter": true
          }
        },
        "product-recommendations": {
          "type": "product-recommendations",
          "settings": {
            "show_product_recommendations": true
          }
        }
      }
    },
    "Luxe": {
      "animate_images": true,
      "animate_page_transition_style": "page-logo",
      "button_style": "shadow",
      "cart_type": "sticky",
      "checkout_accent_color": "#111111",
      "checkout_banner_background_color": "#ffffff",
      "checkout_body_background_color": "#ffffff",
      "checkout_body_font": "Helvetica Neue",
      "checkout_button_color": "#111111",
      "checkout_call_to_action_color": "#a26b25",
      "checkout_error_color": "#ff6d6d",
      "checkout_heading_font": "Helvetica Neue",
      "checkout_input_background_color_mode": "white",
      "checkout_logo_position": "left",
      "checkout_logo_size": "medium",
      "checkout_sidebar_background_color": "#fafafa",
      "checkout_use_header_image": false,
      "color_alt_bg": "#ffffff",
      "color_alt_text": "#333029",
      "color_announcement": "#c67066",
      "color_announcement_text": "#ffffff",
      "color_body_bg": "#fdfbfa",
      "color_body_text": "#333029",
      "color_button": "#c67066",
      "color_button_text": "#ffffff",
      "color_cart_dot": "#c67066",
      "color_drawer_background": "#fdf9f5",
      "color_drawer_text": "#333029",
      "color_image_bg": "#000000",
      "color_image_overlay": "#000000",
      "color_image_overlay_opacity": 10,
      "color_image_text": "#ffffff",
      "color_large_image_bg": "#eee5e0",
      "color_newsletter": "#c67066",
      "color_newsletter_text": "#ffffff",
      "color_sale_price": "#333029",
      "color_sale_tag": "#c67066",
      "color_small_image_bg": "#fdfbfa",
      "desktop_loader_width": 140,
      "mobile_loader_width": 130,
      "product_grid_image_size": "natural",
      "product_hover_details": true,
      "product_hover_image": true,
      "product_image_scatter": false,
      "product_video_style": "muted",
      "type_base_font_family": "futura_n4",
      "type_base_line_height": 1.7,
      "type_base_size": 18,
      "type_base_spacing": "25",
      "type_header_base_size": 50,
      "type_header_capitalize": false,
      "type_header_font_family": "itc_novarese_n5",
      "type_header_line_height": 1.1,
      "type_header_spacing": "0",
      "type_product_capitalize": false,
      "sections": {
        "header": {
          "type": "header",
          "settings": {
            "sticky_index": true,
            "sticky_collection": true,
            "header_search_enable": true,
            "show_announcement": true,
            "show_announcement_home_only": false
          }
        },
        "footer": {
          "type": "footer",
          "settings": {
            "show_newsletter": true,
            "show_social_icons": true,
            "show_payment_icons": false,
            "show_copyright": false
          }
        },
        "newsletter-popup": {
          "type": "newsletter-popup",
          "settings": {
            "mode": "disabled",
            "popup_seconds": 5,
            "popup_days": 30,
            "enable_newsletter": true
          }
        },
        "password-header": {
          "type": "password-header",
          "settings": {}
        },
        "product-recommendations": {
          "type": "product-recommendations",
          "settings": {
            "show_product_recommendations": true
          }
        }
      }
    },
    "Hype": {
      "animate_images": false,
      "animate_page_transition_style": "page-logo",
      "button_style": "shadow",
      "cart_type": "sticky",
      "checkout_accent_color": "#111111",
      "checkout_body_background_color": "#ffffff",
      "checkout_body_font": "Helvetica Neue",
      "checkout_button_color": "#111111",
      "checkout_error_color": "#ff6d6d",
      "checkout_heading_font": "Helvetica Neue",
      "checkout_input_background_color_mode": "white",
      "checkout_logo_position": "left",
      "checkout_logo_size": "medium",
      "checkout_sidebar_background_color": "#fafafa",
      "color_alt_bg": "#000000",
      "color_alt_text": "#ffffff",
      "color_announcement": "#000000",
      "color_announcement_text": "#ffffff",
      "color_body_bg": "#ffffff",
      "color_cart_dot": "#FF2300",
      "color_drawer_background": "#ffffff",
      "color_drawer_text": "#000000",
      "color_image_bg": "#000000",
      "color_image_overlay": "#000000",
      "color_image_overlay_opacity": 10,
      "color_image_text": "#ffffff",
      "color_large_image_bg": "#000000",
      "color_newsletter": "#000000",
      "color_newsletter_text": "#ffffff",
      "color_small_image_bg": "#f2f2f2",
      "desktop_loader_width": 190,
      "mobile_loader_width": 180,
      "product_grid_image_size": "natural",
      "product_hover_details": false,
      "product_hover_image": true,
      "product_image_scatter": true,
      "product_video_style": "muted",
      "type_base_font_family": "basic_commercial_n7",
      "type_base_line_height": 1.3,
      "type_base_size": 20,
      "type_base_spacing": "25",
      "type_header_base_size": 48,
      "type_header_capitalize": true,
      "type_header_font_family": "basic_commercial_n7",
      "type_header_line_height": 0.9,
      "type_header_spacing": "25",
      "type_product_capitalize": true,
      "sections": {
        "header": {
          "type": "header",
          "settings": {
            "sticky_index": true,
            "sticky_collection": true,
            "header_search_enable": true,
            "show_announcement": false
          }
        },
        "footer": {
          "type": "footer",
          "settings": {
            "show_newsletter": false
          }
        },
        "newsletter-popup": {
          "type": "newsletter-popup",
          "settings": {
            "mode": "disabled",
            "popup_seconds": 5,
            "popup_days": 30,
            "enable_newsletter": true
          }
        },
        "product-recommendations": {
          "type": "product-recommendations",
          "settings": {
            "show_product_recommendations": true
          }
        }
      }
    }
  }
}