{
  "sections": {
    "main": {
      "type": "main-page",
      "disabled": true,
      "settings": {}
    },
    "slideshow": {
      "type": "slideshow",
      "blocks": {
        "slideshow-0": {
          "type": "image",
          "settings": {
            "title": "For everyday comfort",
            "title_size": 80,
            "subheading": "The only pair of underwear you will ever want to wear again. Guaranteed!",
            "link": "",
            "link_text": "",
            "color_accent": "rgba(0,0,0,0)",
            "text_align": "vertical-center horizontal-center",
            "image": "shopify:\/\/shop_images\/image00029.jpg",
            "focal_point": "center center"
          }
        }
      },
      "block_order": [
        "slideshow-0"
      ],
      "settings": {
        "style": "arrows",
        "desktop_size": -50,
        "mobile_size": 0,
        "autoplay": false,
        "autoplay_speed": 7
      }
    },
    "16552041332715e691": {
      "type": "advanced-content",
      "blocks": {
        "1655204133f68607ee-0": {
          "type": "image",
          "settings": {
            "image": "shopify:\/\/shop_images\/ajrdiagram3.png",
            "link": "shopify:\/\/collections\/all",
            "image__dk": "shopify:\/\/shop_images\/dk-diagram-desktop_2d0101fe-98e7-42ad-a151-6075eed1f84b.png",
            "link__dk": "shopify:\/\/collections\/all",
            "link__de": "",
            "width": "100%",
            "image_mobile": "shopify:\/\/shop_images\/ajrdiagram-mobile.png",
            "image_mobile__dk": "shopify:\/\/shop_images\/dk-diagram-mobil.png",
            "alignment": "center",
            "button_label": "Get yours now!",
            "button_link": "shopify:\/\/collections\/all",
            "button_style": "primary"
          }
        }
      },
      "block_order": [
        "1655204133f68607ee-0"
      ],
      "settings": {
        "full_width": true,
        "space_around": false,
        "alt": false,
        "main-title": "Why choose ajr underwear?"
      }
    },
    "1655203436b2f63fc3": {
      "type": "text-and-image",
      "settings": {
        "image": "shopify:\/\/shop_images\/tablebox4.png",
        "image2": "shopify:\/\/shop_images\/tablebox-mobil.png",
        "image__dk": "shopify:\/\/shop_images\/dk-table-desktop.png",
        "image2__dk": "shopify:\/\/shop_images\/dk-table-mobil.png",
        "image_width": 700,
        "subtitle": "",
        "title": "Not conviced?",
        "text": "<p>We are very convinced, that you will love our AJR-underwear. Are you convinced? If not, then get yours now! <strong>Always free delivery!<\/strong><\/p>",
        "button_label": "Get your 3-pack now - only 399 kr.!",
        "button_link": "shopify:\/\/collections\/all",
        "button_style": "primary",
        "align_text": "center",
        "layout": "right",
        "alt": true
      }
    },
    "165529959990dfb3d1": {
      "type": "advanced-content",
      "blocks": {
        "1655299599e2b9294c-1": {
          "type": "liquid",
          "settings": {
            "code": "<h2 class=\"h1 text-center\">Athletes use it already<\/h2><p class=\"text-center\">Top professional athletes around the world wear the AJR underwear to achieve their maximum performance getting an edge over their rivals.<\/p>",
            "width": "75%",
            "alignment": "center",
            "button_label_html": "Get your 3-pack now!",
            "button_link_html": "shopify:\/\/collections\/all",
            "button_style_html": "primary"
          }
        }
      },
      "block_order": [
        "1655299599e2b9294c-1"
      ],
      "settings": {
        "full_width": false,
        "space_around": true,
        "alt": false,
        "main-title": ""
      }
    },
    "16552845119f622ada": {
      "type": "testimonials",
      "blocks": {
        "165528451115c30e82-1": {
          "type": "testimonial",
          "settings": {
            "testimonial": "<p><em>When I stand in front of world stars and have to perform at the highest level, it's good to wear some underwear that do not bother me while I’m playing. <\/em><\/p>",
            "image": "shopify:\/\/shop_images\/997F01D1-9DE0-4A2B-890B-DA58870441B8.jpg",
            "author": "Nikolai Baden, Vitesse - latest a Juventus spiller"
          }
        },
        "165528451115c30e82-0": {
          "type": "testimonial",
          "settings": {
            "testimonial": "<p>Arturo Erasmo Vidal Pardo (commonly known as Arturo Vidal) is a Chilean footballer who from 2020 will play as a midfielder for Italian Inter Milan. He has played for FC Barcelona from 2018 to 2020, where he joined from the German big club, FC Bayern Munich.<\/p>",
            "image": "shopify:\/\/shop_images\/image00002.jpg",
            "author": "Arturo Vidal, Inter Milan - Seria A"
          }
        },
        "03e28f4d-0456-42ff-a78b-4a3f88ea0094": {
          "type": "testimonial",
          "settings": {
            "testimonial": "<p>My name is Enock Poulsen I’m a professional boxer. I love wearing the AJR underwear because they are great to wear during training and combat. The comfort is super good, especially when I move around it feels good and flexible to wear compared to other underwear.<\/p>",
            "image": "shopify:\/\/shop_images\/image00001.jpg",
            "author": "Enock Poulsen, Professional boxer (European Champion 2022)"
          }
        }
      },
      "block_order": [
        "165528451115c30e82-1",
        "165528451115c30e82-0",
        "03e28f4d-0456-42ff-a78b-4a3f88ea0094"
      ],
      "settings": {
        "title": "",
        "subtitle": "",
        "align_text": "center",
        "round_images": false,
        "square_images": true,
        "alt": false
      }
    },
    "16552853311791ac1e": {
      "type": "featured-services",
      "blocks": {
        "1655285331d1a8c2c9-0": {
          "type": "service",
          "settings": {
            "title": "No rolling up issues",
            "description": "The unique combination of fabric and design makes the underwear stay in place with every movement.",
            "icon": "shopify:\/\/shop_images\/stof-design.png",
            "uspLinkUrl": ""
          }
        },
        "1655285331d1a8c2c9-1": {
          "type": "service",
          "settings": {
            "title": "Comfortable on the skin",
            "description": "Made of 94% cotton stretch and 6% spandex, giving you a soft and comfortable feel all day.",
            "icon": "shopify:\/\/shop_images\/cotton.png",
            "uspLinkUrl": ""
          }
        },
        "a34d16fd-99d9-41e8-bfdb-c245035fbb05": {
          "type": "service",
          "settings": {
            "title": "Unique flexible fit",
            "description": "Stretchy and flexible fit with a soft elastic waistband for comfort all day.",
            "icon": "shopify:\/\/shop_images\/Unique-flex.png",
            "uspLinkUrl": ""
          }
        },
        "c13dae76-0101-4616-9102-0230402cfff1": {
          "type": "service",
          "settings": {
            "title": "Perfect fit for sports",
            "description": "Designed for sports and everyday comfort. The design and combination of fabrics enables unlimited performance.",
            "icon": "shopify:\/\/shop_images\/perfect-sport.png",
            "uspLinkUrl": ""
          }
        }
      },
      "block_order": [
        "1655285331d1a8c2c9-0",
        "1655285331d1a8c2c9-1",
        "a34d16fd-99d9-41e8-bfdb-c245035fbb05",
        "c13dae76-0101-4616-9102-0230402cfff1"
      ],
      "settings": {
        "title": ""
      }
    },
    "featured-collection": {
      "type": "featured-collection-slider",
      "settings": {
        "title": "Featured collection",
        "description": "",
        "home_featured_products": "all",
        "per_row": "small",
        "alt": false
      }
    },
    "165537058017c25150": {
      "type": "promo",
      "disabled": true,
      "settings": {
        "image": "shopify:\/\/shop_images\/ajrpromo-contrast2.png",
        "image_width": 700,
        "subtitle": "Ajr promotion",
        "title": "Promo for discounts",
        "text": "<p>Pair large text with an image to tell a story, explain a detail about your product, or describe a new promotion.<\/p>",
        "discount__text": "get a test pair",
        "button_label": "Shop now",
        "button_link": "",
        "button_style": "primary",
        "align_text": "center",
        "layout": "left",
        "alt_inner": true,
        "alt": false
      }
    }
  },
  "order": [
    "main",
    "slideshow",
    "16552041332715e691",
    "1655203436b2f63fc3",
    "165529959990dfb3d1",
    "16552845119f622ada",
    "16552853311791ac1e",
    "featured-collection",
    "165537058017c25150"
  ]
}